pegasus_client/__init__.py
pegasus_client/pegasus.py
pegasus_client/pegasus_handler.py
pegasus_client/default_modules/__init__.py
pegasus_client/default_modules/clear.py
pegasus_client/default_modules/connection.py
pegasus_client/default_modules/example.py
pegasus_client/default_modules/exit.py
pegasus_client/default_modules/format.py
pegasus_client/default_modules/help.py
pegasus_client/default_modules/snippet.py
pegasus_client/default_modules/sql.py
pegasus_client/default_modules/update.py
pegasus_client/default_modules/generic/clipboard.py
pegasus_client/default_modules/generic/snippets.py
pegasus_client/img/pegasus_icon.png
pegasus_client/routes/__init__.py
pegasus_client/routes/core.py
pegasus_client/routes/error_handling.py
pegasus_client/routes/sql_routes.py
pegasus_client/templates/home.html
pegasus_client/templates/components/command_grid.html
pegasus_client/templates/components/footer.html
pegasus_client/templates/components/header.html
pegasus_client/templates/components/search_bar.html
pegasus_client/templates/sql/sql_config.html
pegasus_client/templates/sql/sql_creator.html
pegasus_client/templates/sql/modals/command_modals.html
pegasus_client/templates/sql/modals/connection_modals.html
pegasus_client/templates/sql/modals/credential_modals.html
pegasus_client/templates/sql/modals/query_modals.html
pegasus_client-0.17.dist-info/LICENSE
pegasus_client-0.17.dist-info/METADATA
pegasus_client-0.17.dist-info/WHEEL
pegasus_client-0.17.dist-info/top_level.txt
pegasus_client-0.17.dist-info/RECORD
