Metadata-Version: 2.1
Name: pegasus-client
Version: 0.17
Summary: Command-line and web tool with modular interface.
Home-page: https://github.com/euanacampbell/pegasus
Download-URL: https://github.com/euanacampbell/pegasus/archive/refs/heads/master.tar.gz
Author: Euan Campbell
Author-email: dev@euan.app
License: MIT
Keywords: command-line,web,tool
Platform: UNKNOWN
Classifier: Development Status :: 3 - Alpha
Classifier: Intended Audience :: Developers
Classifier: Topic :: Software Development :: Build Tools
Classifier: License :: OSI Approved :: MIT License
Classifier: Programming Language :: Python :: 3
Classifier: Programming Language :: Python :: 3.4
Classifier: Programming Language :: Python :: 3.5
Classifier: Programming Language :: Python :: 3.6
License-File: LICENSE
Requires-Dist: requests
Requires-Dist: pylint
Requires-Dist: PyMySQL
Requires-Dist: pyperclip
Requires-Dist: sqlparse
Requires-Dist: rich
Requires-Dist: psutil
Requires-Dist: gunicorn
Requires-Dist: PyYAML
Requires-Dist: flask
Requires-Dist: pyodbc
Requires-Dist: tabulate
